pw_cli.py
PW_cli-1.0.2.dist-info/LICENSE
PW_cli-1.0.2.dist-info/METADATA
PW_cli-1.0.2.dist-info/WHEEL
PW_cli-1.0.2.dist-info/entry_points.txt
PW_cli-1.0.2.dist-info/top_level.txt
PW_cli-1.0.2.dist-info/RECORD
