Metadata-Version: 2.1
Name: PW-cli
Version: 1.0.2
Summary: Versatile tool for browsing Odoo / OpenERP data
Home-page: http://pw_cli.readthedocs.org/
Author: Florent Xicluna
Author-email: florent.xicluna@gmail.com
License: BSD
Keywords: odoo openerp xml-rpc xmlrpc jsonrpc
Platform: any
Classifier: Development Status :: 5 - Production/Stable
Classifier: Environment :: Console
Classifier: Framework :: Odoo
Classifier: Intended Audience :: Developers
Classifier: License :: OSI Approved :: BSD License
Classifier: Operating System :: OS Independent
Classifier: Programming Language :: Python :: 3.7
Classifier: Programming Language :: Python :: 3.8
Classifier: Programming Language :: Python :: 3.9
Classifier: Programming Language :: Python :: 3.10
Classifier: Topic :: Software Development :: Libraries :: Python Modules
License-File: LICENSE
